jedi_language_server/__init__.py
jedi_language_server/cli.py
jedi_language_server/constants.py
jedi_language_server/initialization_options.py
jedi_language_server/jedi_utils.py
jedi_language_server/py.typed
jedi_language_server/pygls_utils.py
jedi_language_server/server.py
jedi_language_server/text_edit_utils.py
jedi_language_server/type_map.py
jedi_language_server-0.43.0.dist-info/LICENSE
jedi_language_server-0.43.0.dist-info/METADATA
jedi_language_server-0.43.0.dist-info/WHEEL
jedi_language_server-0.43.0.dist-info/entry_points.txt
jedi_language_server-0.43.0.dist-info/RECORD
