Metadata-Version: 2.1
Name: jedi-language-server
Version: 0.43.0
Summary: A language server for Jedi!
Home-page: https://github.com/pappasam/jedi-language-server
License: MIT
Keywords: python,completion,refactoring,lsp,language-server-protocol
Author: Sam Roeca
Author-email: samuel.roeca@gmail.com
Requires-Python: >=3.9,<4.0
Classifier: Development Status :: 4 - Beta
Classifier: Intended Audience :: Developers
Classifier: License :: OSI Approved :: MIT License
Classifier: Operating System :: OS Independent
Classifier: Programming Language :: Python :: 3
Classifier: Programming Language :: Python :: 3.9
Classifier: Programming Language :: Python :: 3.10
Classifier: Programming Language :: Python :: 3.11
Classifier: Programming Language :: Python :: 3.12
Classifier: Programming Language :: Python :: 3.13
Classifier: Topic :: Software Development :: Code Generators
Classifier: Topic :: Software Development :: Libraries :: Python Modules
Classifier: Topic :: Text Editors :: Integrated Development Environments (IDE)
Classifier: Topic :: Utilities
Classifier: Typing :: Typed
Requires-Dist: cattrs (>=23.1.2)
Requires-Dist: docstring-to-markdown (==0.*)
Requires-Dist: jedi (>=0.19.2,<0.20.0)
Requires-Dist: lsprotocol (>=2023.0.1)
Requires-Dist: pygls (>=1.1.0,<2.0.0)
Requires-Dist: typing-extensions (>=4.5.0,<5.0.0) ; python_version < "3.10"
Project-URL: Changelog, https://github.com/pappasam/jedi-language-server/blob/main/CHANGELOG.md
Project-URL: Issues, https://github.com/pappasam/jedi-language-server/issues
Project-URL: Repository, https://github.com/pappasam/jedi-language-server
